eurekaClientShare/client/client.py
eurekaClientShare/client/instance.py
eurekaClientShare/constant/error.py
eurekaClientShare/constant/format.py
eurekaClientShare/constant/http_code.py
eurekaClientShare/constant/path.py
eurekaClientShare/util/request.py
eurekaClientShare-0.2.0.dist-info/LICENSE
eurekaClientShare-0.2.0.dist-info/METADATA
eurekaClientShare-0.2.0.dist-info/WHEEL
eurekaClientShare-0.2.0.dist-info/top_level.txt
eurekaClientShare-0.2.0.dist-info/RECORD
