Metadata-Version: 2.1
Name: eurekaClientShare
Version: 0.2.0
Summary: Simple eureka client
Home-page: https://github.com/santiagoMeloMedina/eurekaClientShare
Author: Santiago Melo Medina
Author-email: santiagodevelopment001@gmail.com
License: UNKNOWN
Platform: UNKNOWN
Classifier: Programming Language :: Python :: 3
Classifier: License :: OSI Approved :: MIT License
Classifier: Operating System :: Unix
Requires-Python: >=3.6
